setup.py
flask_base_library/__init__.py
flask_base_library.egg-info/PKG-INFO
flask_base_library.egg-info/SOURCES.txt
flask_base_library.egg-info/dependency_links.txt
flask_base_library.egg-info/top_level.txt
flask_base_library/DateTimeEncoder/DateTimeEncoder.py
flask_base_library/DateTimeEncoder/__init__.py
flask_base_library/json_data/__init__.py
flask_base_library/json_data/get_json_data.py
flask_base_library/query_parameters/Param.py
flask_base_library/query_parameters/__init__.py
flask_base_library/query_parameters/get_parameters.py