Metadata-Version: 1.0
Name: flask-base-library
Version: 0.1.2
Summary: Flask base library for D Sanders
Home-page: UNKNOWN
Author: David Sanders
Author-email: dsanderscanada@gmail.com
License: MIT
Platform: UNKNOWN
